rubics_cube/VERSION
rubics_cube/__init__.py
rubics_cube/cube.py
rubics_cube/heuristics.py
rubics_cube-0.1.0.dist-info/LICENSE
rubics_cube-0.1.0.dist-info/METADATA
rubics_cube-0.1.0.dist-info/WHEEL
rubics_cube-0.1.0.dist-info/top_level.txt
rubics_cube-0.1.0.dist-info/RECORD
