Metadata-Version: 2.1
Name: rubics-cube
Version: 0.1.0
Summary: A Rubics Cube simulator
Author-email: "Osman F. Bayram" <osmanfbayram@gmail.com>
License: MIT License
Project-URL: source, https://github.com/osbm/rubics-cube
Project-URL: tracker, https://github.com/osbm/rubics-cube/issues
Keywords: rubics,cube,simulator,rubics-cube
Requires-Python: >=3.7
License-File: LICENSE
Requires-Dist: numpy
Requires-Dist: matplotlib
